azure/ai/translation/text/__init__.py
azure/ai/translation/text/_client.py
azure/ai/translation/text/_configuration.py
azure/ai/translation/text/_model_base.py
azure/ai/translation/text/_patch.py
azure/ai/translation/text/_serialization.py
azure/ai/translation/text/_vendor.py
azure/ai/translation/text/_version.py
azure/ai/translation/text/py.typed
azure/ai/translation/text/_operations/__init__.py
azure/ai/translation/text/_operations/_operations.py
azure/ai/translation/text/_operations/_patch.py
azure/ai/translation/text/aio/__init__.py
azure/ai/translation/text/aio/_client.py
azure/ai/translation/text/aio/_configuration.py
azure/ai/translation/text/aio/_patch.py
azure/ai/translation/text/aio/_vendor.py
azure/ai/translation/text/aio/_operations/__init__.py
azure/ai/translation/text/aio/_operations/_operations.py
azure/ai/translation/text/aio/_operations/_patch.py
azure/ai/translation/text/models/__init__.py
azure/ai/translation/text/models/_enums.py
azure/ai/translation/text/models/_models.py
azure/ai/translation/text/models/_patch.py
azure_ai_translation_text-1.0.1.dist-info/LICENSE
azure_ai_translation_text-1.0.1.dist-info/METADATA
azure_ai_translation_text-1.0.1.dist-info/WHEEL
azure_ai_translation_text-1.0.1.dist-info/top_level.txt
azure_ai_translation_text-1.0.1.dist-info/RECORD
